setup.cfg
setup.py
django_opencred.egg-info/PKG-INFO
django_opencred.egg-info/SOURCES.txt
django_opencred.egg-info/dependency_links.txt
django_opencred.egg-info/not-zip-safe
django_opencred.egg-info/requires.txt
django_opencred.egg-info/top_level.txt
opencred/__init__.py
opencred/apps.py
opencred/middleware.py
opencred/password_validation.py
opencred/settings.py
opencred/signals.py
opencred/management/__init__.py
opencred/management/commands/__init__.py
opencred/management/commands/opencred.py
opencred/tests/__init__.py
opencred/tests/settings.py
opencred/tests/test_middleware.py
opencred/tests/test_redirects.py
opencred/tests/test_signals.py
opencred/tests/urls.py